hardware/__init__.py
hardware/arduino.py
hardware/camera.py
hardware/system.py
hardware/mock/__init__.py
hardware/mock/arduino.py
hardware/mock/camera.py
hardware/mock/system.py
server/__init__.py
server/cameraserver.py
server/ioserver.py
server/webserver.py
web/__init__.py
web/scripts/__init__.py
web/static/__init__.py
pyedurov2_simtind-0.0.3.dist-info/LICENSE
pyedurov2_simtind-0.0.3.dist-info/METADATA
pyedurov2_simtind-0.0.3.dist-info/WHEEL
pyedurov2_simtind-0.0.3.dist-info/entry_points.txt
pyedurov2_simtind-0.0.3.dist-info/top_level.txt
pyedurov2_simtind-0.0.3.dist-info/RECORD
